pyscenes/__init__.py
pyscenes/base_scene.py
pyscenes/future_features.py
pyscenes/main.py
pyscenes/pyscenes.py
PyScenes-0.0.1.dist-info/LICENSE.md
PyScenes-0.0.1.dist-info/METADATA
PyScenes-0.0.1.dist-info/WHEEL
PyScenes-0.0.1.dist-info/top_level.txt
PyScenes-0.0.1.dist-info/RECORD
