Metadata-Version: 2.1
Name: PyScenes
Version: 0.0.1
Summary: PyScenes is a PyGame 2 wrapper for beginners.
Home-page: UNKNOWN
Author: UNKNOWN
Author-email: treygilliland3@gmail.com
License: UNKNOWN
Platform: UNKNOWN
